mysam/__init__.py
mysam/tag_const.py
mysam/tag_const_inflect.py
mysam/tagcoder.py
mysam/tagconfig.py
mysam/taginflector.py
mysam/tagmaker.py
mysam/config/tag.config
mysam_tagmanager-0.4.dist-info/LICENSE
mysam_tagmanager-0.4.dist-info/METADATA
mysam_tagmanager-0.4.dist-info/WHEEL
mysam_tagmanager-0.4.dist-info/top_level.txt
mysam_tagmanager-0.4.dist-info/RECORD
