Metadata-Version: 2.1
Name: mysam-tagmanager
Version: 0.4
Summary: Mysam: Arabic tags manager
Home-page: http://pypi.python.com/projects/mysam-tagmanager/
Author: Taha Zerrouki
Author-email: taha_zerrouki@hotmail.com
License: GPL
Platform: UNKNOWN
Classifier: Development Status :: 5 - Production/Stable
Classifier: Natural Language :: Arabic
Classifier: Intended Audience :: Developers
Classifier: Operating System :: OS Independent
Classifier: Programming Language :: Python
Classifier: Topic :: Text Processing :: Linguistic
